{
  "metric": "last_sale_price",
  "aggregation": "hexbin",
  "hex_size_deg": 0.001,
  "cell_count": 18,
  "cells": [
    {
      "q": -81823,
      "r": 18048,
      "lat": 42.19493,
      "lng": -122.7345,
      "count": 1,
      "median": 565000,
      "mean": 565000.0,
      "min": 565000,
      "max": 565000
    },
    {
      "q": -81826,
      "r": 18050,
      "lat": 42.198437,
      "lng": -122.739,
      "count": 1,
      "median": 750000,
      "mean": 750000.0,
      "min": 750000,
      "max": 750000
    },
    {
      "q": -81813,
      "r": 18050,
      "lat": 42.199606,
      "lng": -122.7195,
      "count": 4,
      "median": 384000,
      "mean": 217500.0,
      "min": 34000,
      "max": 395000
    },
    {
      "q": -81815,
      "r": 18050,
      "lat": 42.199606,
      "lng": -122.7225,
      "count": 20,
      "median": 515000,
      "mean": 501725.0,
      "min": 55000,
      "max": 755000
    },
    {
      "q": -81814,
      "r": 18051,
      "lat": 42.200775,
      "lng": -122.721,
      "count": 4,
      "median": 630000,
      "mean": 555000.0,
      "min": 165000,
      "max": 800000
    },
    {
      "q": -81814,
      "r": 18050,
      "lat": 42.198437,
      "lng": -122.721,
      "count": 12,
      "median": 550000,
      "mean": 462391.67,
      "min": 120000,
      "max": 830000
    },
    {
      "q": -81799,
      "r": 18046,
      "lat": 42.190255,
      "lng": -122.6985,
      "count": 8,
      "median": 579000,
      "mean": 606312.5,
      "min": 407500,
      "max": 850000
    },
    {
      "q": -81812,
      "r": 18050,
      "lat": 42.198437,
      "lng": -122.718,
      "count": 1,
      "median": 101400,
      "mean": 101400.0,
      "min": 101400,
      "max": 101400
    },
    {
      "q": -81815,
      "r": 18049,
      "lat": 42.197268,
      "lng": -122.7225,
      "count": 3,
      "median": 355000,
      "mean": 415666.67,
      "min": 352000,
      "max": 540000
    },
    {
      "q": -81813,
      "r": 18049,
      "lat": 42.197268,
      "lng": -122.7195,
      "count": 1,
      "median": 144000,
      "mean": 144000.0,
      "min": 144000,
      "max": 144000
    },
    {
      "q": -81784,
      "r": 18048,
      "lat": 42.193761,
      "lng": -122.676,
      "count": 3,
      "median": 100000,
      "mean": 204166.67,
      "min": 55500,
      "max": 457000
    },
    {
      "q": -81802,
      "r": 18049,
      "lat": 42.196099,
      "lng": -122.703,
      "count": 1,
      "median": 10,
      "mean": 10.0,
      "min": 10,
      "max": 10
    },
    {
      "q": -81801,
      "r": 18048,
      "lat": 42.19493,
      "lng": -122.7015,
      "count": 1,
      "median": 58700,
      "mean": 58700.0,
      "min": 58700,
      "max": 58700
    },
    {
      "q": -81786,
      "r": 18047,
      "lat": 42.191424,
      "lng": -122.679,
      "count": 4,
      "median": 430000,
      "mean": 347650.0,
      "min": 82600,
      "max": 504000
    },
    {
      "q": -81800,
      "r": 18047,
      "lat": 42.191424,
      "lng": -122.7,
      "count": 9,
      "median": 565000,
      "mean": 717355.56,
      "min": 81000,
      "max": 1675000
    },
    {
      "q": -81801,
      "r": 18046,
      "lat": 42.190255,
      "lng": -122.7015,
      "count": 8,
      "median": 313000,
      "mean": 367875.0,
      "min": 180000,
      "max": 680000
    },
    {
      "q": -81802,
      "r": 18047,
      "lat": 42.191424,
      "lng": -122.703,
      "count": 4,
      "median": 581500,
      "mean": 470750.0,
      "min": 147500,
      "max": 715000
    },
    {
      "q": -81779,
      "r": 18049,
      "lat": 42.197268,
      "lng": -122.6685,
      "count": 1,
      "median": 775000,
      "mean": 775000.0,
      "min": 775000,
      "max": 775000
    }
  ]
}